xplt/__init__.py
xplt/base.py
xplt/colors.py
xplt/hooks.py
xplt/line.py
xplt/particles.py
xplt/phasespace.py
xplt/properties.py
xplt/timestructure.py
xplt/twiss.py
xplt/util.py
xplt/xplt.mplstyle
xplt-0.12.3.dist-info/licenses/LICENSE
xplt-0.12.3.dist-info/METADATA
xplt-0.12.3.dist-info/WHEEL
xplt-0.12.3.dist-info/top_level.txt
xplt-0.12.3.dist-info/RECORD
