Metadata-Version: 2.4
Name: xplt
Version: 0.12.3
Summary: Plotting for Xsuite
Author-email: "Philipp Niedermayer (github.com/eltos)" <eltos@outlook.de>
License:                                  Apache License
Project-URL: homepage, https://github.com/eltos/xplt
Project-URL: documentation, https://xsuite.github.io/xplt
Project-URL: repository, https://github.com/xsuite/xplt
Keywords: python
Classifier: Development Status :: 4 - Beta
Classifier: License :: OSI Approved :: Apache Software License
Classifier: Topic :: Scientific/Engineering :: Physics
Classifier: Topic :: Scientific/Engineering :: Visualization
Classifier: Framework :: Matplotlib
Classifier: Programming Language :: Python :: 3
Requires-Python: >=3.10
License-File: LICENSE
Requires-Dist: matplotlib>=3.6
Requires-Dist: numpy>=1.17.0
Requires-Dist: scipy>=1.2.0
Provides-Extra: minimal
Provides-Extra: recommended
Requires-Dist: pint>=0.24.1; extra == "recommended"
Provides-Extra: full
Requires-Dist: pint>=0.24.1; extra == "full"
Requires-Dist: pandas; extra == "full"
Dynamic: license-file
